[{"x": 5692.9, "y": 3650.1, "building": "21", "floor": 1, "room_id": ""}, {"x": 6141.9, "y": 4610.1, "building": "21", "floor": 1, "room_id": ""}, {"x": 5942.4, "y": 4435.1, "building": "21", "floor": 1, "room_id": ""}, {"x": 5942.4, "y": 4660.1, "building": "21", "floor": 1, "room_id": ""}, {"x": 5232.0, "y": 563.0, "building": "21", "floor": 1, "room_id": ""}, {"x": 1020.6, "y": 3204.5, "building": "21", "floor": 1, "room_id": ""}, {"x": 1229.1, "y": 3282.5, "building": "21", "floor": 1, "room_id": "21151"}, {"x": 3856.9, "y": 3210.5, "building": "21", "floor": 2, "room_id": ""}, {"x": 1806.9, "y": 3712.5, "building": "21", "floor": 2, "room_id": "21213"}, {"x": 1915.9, "y": 3706.8, "building": "21", "floor": 2, "room_id": "21212"}, {"x": 1716.8, "y": 3712.5, "building": "21", "floor": 2, "room_id": "21213"}, {"x": 1629.1, "y": 3712.5, "building": "21", "floor": 2, "room_id": "21213"}, {"x": 3856.9, "y": 3230.0, "building": "21", "floor": 2, "room_id": ""}, {"x": 3856.9, "y": 3288.5, "building": "21", "floor": 2, "room_id": ""}, {"x": 4829.0, "y": 2218.1, "building": "21", "floor": 2, "room_id": ""}, {"x": 816.1, "y": 3749.5, "building": "21", "floor": 2, "room_id": ""}, {"x": 3004.8, "y": 3526.7, "building": "21", "floor": 2, "room_id": ""}, {"x": 3798.2, "y": 3842.5, "building": "21", "floor": 2, "room_id": ""}, {"x": 1686.4, "y": 3466.3, "building": "21", "floor": 2, "room_id": "21213"}, {"x": 1812.6, "y": 3472.5, "building": "21", "floor": 2, "room_id": "21213"}, {"x": 1906.1, "y": 3472.5, "building": "21", "floor": 2, "room_id": "21212"}, {"x": 3768.9, "y": 3500.5, "building": "21", "floor": 2, "room_id": ""}, {"x": 3768.9, "y": 3411.5, "building": "21", "floor": 2, "room_id": ""}, {"x": 2226.4, "y": 3722.8, "building": "21", "floor": 2, "room_id": "21212"}, {"x": 2287.3, "y": 3727.4, "building": "21", "floor": 2, "room_id": "21212"}, {"x": 2128.9, "y": 3715.5, "building": "21", "floor": 2, "room_id": "21212"}, {"x": 2189.8, "y": 3720.1, "building": "21", "floor": 2, "room_id": "21212"}, {"x": 2033.4, "y": 3708.3, "building": "21", "floor": 2, "room_id": "21212"}, {"x": 2094.3, "y": 3712.9, "building": "21", "floor": 2, "room_id": "21212"}, {"x": 1937.9, "y": 3701.1, "building": "21", "floor": 2, "room_id": "21212"}, {"x": 1998.8, "y": 3705.7, "building": "21", "floor": 2, "room_id": "21212"}, {"x": 5206.9, "y": 2612.0, "building": "21", "floor": 2, "room_id": "21207"}, {"x": 5121.9, "y": 2612.0, "building": "21", "floor": 2, "room_id": "21207"}, {"x": 6245.7, "y": 3897.5, "building": "21", "floor": 2, "room_id": ""}, {"x": 2107.6, "y": 1164.4, "building": "21", "floor": 2, "room_id": ""}, {"x": 444.6, "y": 3741.5, "building": "21", "floor": 2, "room_id": ""}, {"x": 437.6, "y": 3741.5, "building": "21", "floor": 2, "room_id": ""}, {"x": 664.7, "y": 3244.4, "building": "21", "floor": 2, "room_id": ""}, {"x": 2157.6, "y": 2162.0, "building": "21", "floor": 2, "room_id": ""}, {"x": 2687.7, "y": 2090.4, "building": "21", "floor": 2, "room_id": ""}, {"x": 1978.4, "y": 2937.4, "building": "21", "floor": 2, "room_id": ""}, {"x": 576.6, "y": 3512.2, "building": "21", "floor": 2, "room_id": ""}, {"x": 524.6, "y": 3477.2, "building": "21", "floor": 2, "room_id": ""}, {"x": 693.6, "y": 3392.0, "building": "21", "floor": 2, "room_id": ""}, {"x": 541.1, "y": 3749.5, "building": "21", "floor": 2, "room_id": ""}, {"x": 577.1, "y": 3745.5, "building": "21", "floor": 2, "room_id": ""}, {"x": 720.1, "y": 3749.5, "building": "21", "floor": 2, "room_id": ""}, {"x": 635.1, "y": 3749.5, "building": "21", "floor": 2, "room_id": ""}, {"x": 731.1, "y": 3749.5, "building": "21", "floor": 2, "room_id": ""}, {"x": 816.1, "y": 3749.5, "building": "21", "floor": 2, "room_id": ""}, {"x": 1716.8, "y": 3712.5, "building": "21", "floor": 2, "room_id": "21213"}, {"x": 1806.9, "y": 3712.5, "building": "21", "floor": 2, "room_id": "21213"}, {"x": 1994.1, "y": 3712.7, "building": "21", "floor": 2, "room_id": "21212"}, {"x": 2128.9, "y": 3715.5, "building": "21", "floor": 2, "room_id": "21212"}, {"x": 2349.1, "y": 3754.2, "building": "21", "floor": 2, "room_id": "21212"}, {"x": 3780.4, "y": 1137.4, "building": "21", "floor": 2, "room_id": ""}, {"x": 4663.6, "y": 1642.1, "building": "21", "floor": 2, "room_id": ""}, {"x": 3679.1, "y": 1902.6, "building": "21", "floor": 2, "room_id": ""}, {"x": 4067.2, "y": 2289.7, "building": "21", "floor": 2, "room_id": ""}, {"x": 4859.0, "y": 2188.0, "building": "21", "floor": 2, "room_id": ""}, {"x": 5121.9, "y": 2612.0, "building": "21", "floor": 2, "room_id": "21207"}, {"x": 3856.9, "y": 3347.0, "building": "21", "floor": 2, "room_id": ""}, {"x": 3690.8, "y": 3644.7, "building": "21", "floor": 2, "room_id": ""}, {"x": 4988.3, "y": 4142.1, "building": "21", "floor": 2, "room_id": ""}, {"x": 6363.7, "y": 3897.5, "building": "21", "floor": 2, "room_id": ""}, {"x": 1784.9, "y": 3182.0, "building": "21", "floor": 2, "room_id": ""}, {"x": 1653.8, "y": 3355.0, "building": "21", "floor": 2, "room_id": "21213"}, {"x": 4106.7, "y": 1086.6, "building": "21", "floor": 2, "room_id": ""}, {"x": 4665.2, "y": 2255.7, "building": "21", "floor": 2, "room_id": ""}, {"x": 3006.8, "y": 3531.9, "building": "21", "floor": 2, "room_id": ""}, {"x": 5109.4, "y": 2384.6, "building": "21", "floor": 2, "room_id": ""}, {"x": 5109.4, "y": 2456.4, "building": "21", "floor": 2, "room_id": ""}, {"x": 5392.8, "y": 2442.3, "building": "21", "floor": 2, "room_id": ""}, {"x": 3330.6, "y": 2567.1, "building": "21", "floor": 3, "room_id": "21314"}, {"x": 3403.3, "y": 2639.9, "building": "21", "floor": 3, "room_id": "21315"}, {"x": 1533.1, "y": 3230.9, "building": "21", "floor": 3, "room_id": ""}, {"x": 1364.1, "y": 3065.9, "building": "21", "floor": 3, "room_id": ""}, {"x": 1482.1, "y": 3130.2, "building": "21", "floor": 3, "room_id": "21306"}, {"x": 1223.6, "y": 3117.1, "building": "21", "floor": 3, "room_id": ""}, {"x": 1349.6, "y": 2773.6, "building": "21", "floor": 3, "room_id": ""}, {"x": 1349.6, "y": 2773.6, "building": "21", "floor": 3, "room_id": ""}, {"x": 1094.6, "y": 2773.6, "building": "21", "floor": 3, "room_id": ""}, {"x": 1094.6, "y": 2773.6, "building": "21", "floor": 3, "room_id": ""}, {"x": 1077.1, "y": 3033.4, "building": "21", "floor": 3, "room_id": ""}, {"x": 1296.3, "y": 3027.4, "building": "21", "floor": 3, "room_id": ""}, {"x": 1292.3, "y": 3027.4, "building": "21", "floor": 3, "room_id": ""}, {"x": 1168.3, "y": 3027.4, "building": "21", "floor": 3, "room_id": ""}, {"x": 912.1, "y": 3230.9, "building": "21", "floor": 3, "room_id": ""}, {"x": 2536.5, "y": 2373.4, "building": "21", "floor": 3, "room_id": "21309"}, {"x": 1287.6, "y": 3470.5, "building": "21", "floor": 3, "room_id": ""}, {"x": 1938.4, "y": 3079.7, "building": "21", "floor": 3, "room_id": "21306"}, {"x": 2242.7, "y": 2561.2, "building": "21", "floor": 3, "room_id": "21308"}, {"x": 2242.7, "y": 2561.2, "building": "21", "floor": 3, "room_id": "21308"}, {"x": 3460.7, "y": 3096.8, "building": "21", "floor": 3, "room_id": ""}, {"x": 3554.6, "y": 3190.7, "building": "21", "floor": 3, "room_id": "21316"}, {"x": 3407.9, "y": 2918.8, "building": "21", "floor": 3, "room_id": "21315"}, {"x": 1985.7, "y": 3463.7, "building": "21", "floor": 3, "room_id": ""}, {"x": 1006.1, "y": 4702.8, "building": "21", "floor": 3, "room_id": ""}, {"x": 921.1, "y": 4702.8, "building": "21", "floor": 3, "room_id": ""}, {"x": 2763.2, "y": 4920.3, "building": "21", "floor": 3, "room_id": "21304"}, {"x": 2763.2, "y": 4920.3, "building": "21", "floor": 3, "room_id": "21304"}, {"x": 3031.8, "y": 4664.4, "building": "21", "floor": 3, "room_id": ""}, {"x": 2529.9, "y": 4745.5, "building": "21", "floor": 3, "room_id": ""}, {"x": 2832.7, "y": 4806.0, "building": "21", "floor": 3, "room_id": ""}, {"x": 1442.1, "y": 4702.8, "building": "21", "floor": 3, "room_id": ""}, {"x": 1526.6, "y": 4702.8, "building": "21", "floor": 3, "room_id": ""}, {"x": 4359.6, "y": 4788.2, "building": "21", "floor": 3, "room_id": "21302"}, {"x": 4731.6, "y": 4425.3, "building": "21", "floor": 3, "room_id": "21302"}, {"x": 4998.2, "y": 4147.4, "building": "21", "floor": 3, "room_id": "21301"}, {"x": 5206.3, "y": 3779.5, "building": "21", "floor": 3, "room_id": "21301"}, {"x": 5145.8, "y": 3840.0, "building": "21", "floor": 3, "room_id": "21301"}, {"x": 5815.5, "y": 2155.0, "building": "21", "floor": 3, "room_id": ""}, {"x": 5995.8, "y": 2335.3, "building": "21", "floor": 3, "room_id": ""}, {"x": 4867.2, "y": 4289.7, "building": "21", "floor": 3, "room_id": "21301"}, {"x": 766.6, "y": 3134.9, "building": "21", "floor": 3, "room_id": ""}, {"x": 649.2, "y": 3312.4, "building": "21", "floor": 3, "room_id": ""}, {"x": 824.1, "y": 3339.9, "building": "21", "floor": 3, "room_id": ""}, {"x": 3195.2, "y": 2531.1, "building": "21", "floor": 3, "room_id": "21313"}, {"x": 2762.2, "y": 1900.4, "building": "21", "floor": 3, "room_id": "21310"}, {"x": 2829.2, "y": 1794.4, "building": "21", "floor": 3, "room_id": "21310"}, {"x": 2694.2, "y": 1794.4, "building": "21", "floor": 3, "room_id": "21311"}, {"x": 2694.2, "y": 2136.8, "building": "21", "floor": 3, "room_id": "21309"}, {"x": 4099.8, "y": 3245.3, "building": "21", "floor": 4, "room_id": "21415"}, {"x": 4027.2, "y": 3318.0, "building": "21", "floor": 4, "room_id": "21416"}, {"x": 3947.4, "y": 3106.4, "building": "21", "floor": 4, "room_id": "21412"}, {"x": 3947.4, "y": 3311.3, "building": "21", "floor": 4, "room_id": "21417"}, {"x": 4099.8, "y": 3172.4, "building": "21", "floor": 4, "room_id": "21414"}, {"x": 4027.2, "y": 3099.7, "building": "21", "floor": 4, "room_id": "21413"}, {"x": 2108.8, "y": 3932.0, "building": "21", "floor": 4, "room_id": "21427"}, {"x": 2036.7, "y": 3859.9, "building": "21", "floor": 4, "room_id": "21428"}, {"x": 2035.6, "y": 3786.7, "building": "21", "floor": 4, "room_id": "21429"}, {"x": 2181.3, "y": 3932.3, "building": "21", "floor": 4, "room_id": "21426"}, {"x": 2864.8, "y": 2023.9, "building": "21", "floor": 4, "room_id": "21407"}, {"x": 2658.6, "y": 2023.9, "building": "21", "floor": 4, "room_id": "21404"}, {"x": 2871.9, "y": 1944.5, "building": "21", "floor": 4, "room_id": "21406"}, {"x": 3413.3, "y": 2484.4, "building": "21", "floor": 4, "room_id": "21409"}, {"x": 3486.6, "y": 2557.7, "building": "21", "floor": 4, "room_id": "21410"}, {"x": 3485.7, "y": 2628.9, "building": "21", "floor": 4, "room_id": "21411"}, {"x": 3340.7, "y": 2484.0, "building": "21", "floor": 4, "room_id": "21408"}, {"x": 1678.6, "y": 3282.9, "building": "21", "floor": 4, "room_id": "21430"}, {"x": 1534.1, "y": 3187.4, "building": "21", "floor": 4, "room_id": "21401"}, {"x": 1534.1, "y": 3274.4, "building": "21", "floor": 4, "room_id": "21430"}, {"x": 3356.3, "y": 3659.4, "building": "21", "floor": 4, "room_id": "21418"}, {"x": 3211.3, "y": 3804.4, "building": "21", "floor": 4, "room_id": "21419"}, {"x": 2724.3, "y": 4545.9, "building": "21", "floor": 4, "room_id": "21423"}, {"x": 2651.6, "y": 4473.2, "building": "21", "floor": 4, "room_id": "21424"}, {"x": 2864.8, "y": 4393.8, "building": "21", "floor": 4, "room_id": "21420"}, {"x": 2658.6, "y": 4393.8, "building": "21", "floor": 4, "room_id": "21425"}, {"x": 2799.2, "y": 4545.9, "building": "21", "floor": 4, "room_id": "21422"}, {"x": 2871.9, "y": 4473.2, "building": "21", "floor": 4, "room_id": "21421"}, {"x": 2784.2, "y": 1911.0, "building": "21", "floor": 4, "room_id": "21405"}, {"x": 2335.4, "y": 2556.1, "building": "21", "floor": 4, "room_id": "21452"}, {"x": 2408.8, "y": 2243.7, "building": "21", "floor": 4, "room_id": "21404"}, {"x": 1869.6, "y": 2932.8, "building": "21", "floor": 4, "room_id": "21401"}, {"x": 2182.6, "y": 2709.0, "building": "21", "floor": 4, "room_id": "21452"}, {"x": 2111.9, "y": 2779.7, "building": "21", "floor": 4, "room_id": "21452"}, {"x": 1942.1, "y": 3076.0, "building": "21", "floor": 4, "room_id": "21401"}, {"x": 1686.4, "y": 3670.5, "building": "21", "floor": 4, "room_id": "21430"}, {"x": 1686.4, "y": 3670.5, "building": "21", "floor": 4, "room_id": "21430"}, {"x": 1678.6, "y": 3282.9, "building": "21", "floor": 4, "room_id": "21430"}, {"x": 1482.1, "y": 3130.2, "building": "21", "floor": 4, "room_id": "21401"}, {"x": 1223.6, "y": 3117.1, "building": "21", "floor": 4, "room_id": "21400"}, {"x": 1077.1, "y": 3033.4, "building": "21", "floor": 4, "room_id": "21400"}, {"x": 1258.1, "y": 3027.4, "building": "21", "floor": 4, "room_id": "21400"}, {"x": 1168.3, "y": 3027.4, "building": "21", "floor": 4, "room_id": "21400"}, {"x": 912.1, "y": 3230.9, "building": "21", "floor": 4, "room_id": "21400"}, {"x": 949.6, "y": 2828.7, "building": "21", "floor": 4, "room_id": "21400"}, {"x": 1313.2, "y": 3093.5, "building": "21", "floor": 4, "room_id": "21400"}, {"x": 1347.9, "y": 3093.5, "building": "21", "floor": 4, "room_id": "21400"}, {"x": 4099.8, "y": 3245.3, "building": "21", "floor": 5, "room_id": "21519"}, {"x": 4027.2, "y": 3318.0, "building": "21", "floor": 5, "room_id": "21520"}, {"x": 3947.4, "y": 3106.4, "building": "21", "floor": 5, "room_id": "21516"}, {"x": 3947.4, "y": 3311.3, "building": "21", "floor": 5, "room_id": "21521"}, {"x": 4099.8, "y": 3172.4, "building": "21", "floor": 5, "room_id": "21518"}, {"x": 4027.2, "y": 3099.7, "building": "21", "floor": 5, "room_id": "21517"}, {"x": 2864.8, "y": 2023.9, "building": "21", "floor": 5, "room_id": "21511"}, {"x": 2658.6, "y": 2023.9, "building": "21", "floor": 5, "room_id": "21506"}, {"x": 2871.9, "y": 1944.5, "building": "21", "floor": 5, "room_id": "21510"}, {"x": 1678.6, "y": 3282.9, "building": "21", "floor": 5, "room_id": "21534"}, {"x": 2724.3, "y": 4545.9, "building": "21", "floor": 5, "room_id": "21528"}, {"x": 2864.8, "y": 4393.8, "building": "21", "floor": 5, "room_id": "21526"}, {"x": 2658.6, "y": 4393.8, "building": "21", "floor": 5, "room_id": "21529"}, {"x": 2799.2, "y": 4545.9, "building": "21", "floor": 5, "room_id": "21527"}, {"x": 3437.5, "y": 2715.1, "building": "21", "floor": 5, "room_id": "21515"}, {"x": 3437.5, "y": 2715.1, "building": "21", "floor": 5, "room_id": "21515"}, {"x": 3258.6, "y": 2536.2, "building": "21", "floor": 5, "room_id": "21512"}, {"x": 3258.6, "y": 2536.2, "building": "21", "floor": 5, "room_id": "21512"}, {"x": 2108.8, "y": 2485.7, "building": "21", "floor": 5, "room_id": "21504"}, {"x": 2036.7, "y": 2557.8, "building": "21", "floor": 5, "room_id": "21503"}, {"x": 2035.6, "y": 2631.0, "building": "21", "floor": 5, "room_id": "21502"}, {"x": 2181.3, "y": 2485.4, "building": "21", "floor": 5, "room_id": "21505"}, {"x": 3486.8, "y": 3859.9, "building": "21", "floor": 5, "room_id": "21523"}, {"x": 3414.6, "y": 3932.0, "building": "21", "floor": 5, "room_id": "21524"}, {"x": 3341.4, "y": 3933.1, "building": "21", "floor": 5, "room_id": "21525"}, {"x": 3487.1, "y": 3787.4, "building": "21", "floor": 5, "room_id": "21522"}, {"x": 2263.6, "y": 3883.1, "building": "21", "floor": 5, "room_id": "21530"}, {"x": 2263.6, "y": 3883.1, "building": "21", "floor": 5, "room_id": "21530"}, {"x": 2085.7, "y": 3705.2, "building": "21", "floor": 5, "room_id": "21533"}, {"x": 2085.7, "y": 3705.2, "building": "21", "floor": 5, "room_id": "21533"}, {"x": 2651.6, "y": 1944.5, "building": "21", "floor": 5, "room_id": "21507"}, {"x": 2724.3, "y": 1871.8, "building": "21", "floor": 5, "room_id": "21508"}, {"x": 2799.2, "y": 1871.8, "building": "21", "floor": 5, "room_id": "21509"}, {"x": 1534.1, "y": 3230.9, "building": "21", "floor": 5, "room_id": "21534"}, {"x": 1482.1, "y": 3130.2, "building": "21", "floor": 5, "room_id": "21501"}, {"x": 1503.1, "y": 3135.4, "building": "21", "floor": 5, "room_id": "21501"}, {"x": 1077.1, "y": 3065.9, "building": "21", "floor": 5, "room_id": "21500"}, {"x": 1258.1, "y": 3027.4, "building": "21", "floor": 5, "room_id": "21500"}, {"x": 1168.3, "y": 3027.4, "building": "21", "floor": 5, "room_id": "21500"}, {"x": 912.1, "y": 3230.9, "building": "21", "floor": 5, "room_id": "21500"}, {"x": 949.6, "y": 2828.7, "building": "21", "floor": 5, "room_id": "21500"}, {"x": 1313.2, "y": 3093.5, "building": "21", "floor": 5, "room_id": "21500"}, {"x": 1347.9, "y": 3093.5, "building": "21", "floor": 5, "room_id": "21500"}, {"x": 1721.1, "y": 3134.9, "building": "21", "floor": 5, "room_id": "21501"}, {"x": 3934.2, "y": 3108.2, "building": "21", "floor": 6, "room_id": "21611"}, {"x": 3531.7, "y": 3607.8, "building": "21", "floor": 6, "room_id": "21615"}, {"x": 3155.3, "y": 3981.0, "building": "21", "floor": 6, "room_id": "21617"}, {"x": 2779.0, "y": 4354.2, "building": "21", "floor": 6, "room_id": "21619"}, {"x": 3620.4, "y": 3519.8, "building": "21", "floor": 6, "room_id": "21614"}, {"x": 2867.7, "y": 4266.2, "building": "21", "floor": 6, "room_id": "21618"}, {"x": 2921.3, "y": 2087.8, "building": "21", "floor": 6, "room_id": "21606"}, {"x": 2418.9, "y": 2485.6, "building": "21", "floor": 6, "room_id": "21602"}, {"x": 2507.6, "y": 2397.6, "building": "21", "floor": 6, "room_id": "21603"}, {"x": 2986.7, "y": 2377.0, "building": "21", "floor": 6, "room_id": "21607"}, {"x": 3359.9, "y": 2753.4, "building": "21", "floor": 6, "room_id": "21609"}, {"x": 3645.0, "y": 3040.9, "building": "21", "floor": 6, "room_id": "21610"}, {"x": 3271.8, "y": 2664.6, "building": "21", "floor": 6, "room_id": "21608"}, {"x": 2552.1, "y": 4103.6, "building": "21", "floor": 6, "room_id": "21622"}, {"x": 2594.4, "y": 4537.3, "building": "21", "floor": 6, "room_id": "21621"}, {"x": 2484.6, "y": 4546.6, "building": "21", "floor": 6, "room_id": "21621"}, {"x": 3996.7, "y": 3146.6, "building": "21", "floor": 6, "room_id": "21611"}, {"x": 1552.3, "y": 3167.4, "building": "21", "floor": 6, "room_id": ""}, {"x": 1026.2, "y": 3088.4, "building": "21", "floor": 6, "room_id": ""}, {"x": 1419.3, "y": 2865.5, "building": "21", "floor": 6, "room_id": ""}, {"x": 1419.8, "y": 2799.6, "building": "21", "floor": 6, "room_id": ""}, {"x": 1418.5, "y": 2957.5, "building": "21", "floor": 6, "room_id": ""}, {"x": 1419.0, "y": 2891.6, "building": "21", "floor": 6, "room_id": ""}, {"x": 1420.0, "y": 2773.5, "building": "21", "floor": 6, "room_id": ""}, {"x": 1420.6, "y": 2707.6, "building": "21", "floor": 6, "room_id": "21653"}, {"x": 1049.9, "y": 3004.4, "building": "21", "floor": 6, "room_id": ""}, {"x": 1050.8, "y": 2904.4, "building": "21", "floor": 6, "room_id": ""}, {"x": 1050.2, "y": 2970.4, "building": "21", "floor": 6, "room_id": ""}, {"x": 1051.7, "y": 2804.4, "building": "21", "floor": 6, "room_id": ""}, {"x": 1051.1, "y": 2870.4, "building": "21", "floor": 6, "room_id": ""}, {"x": 1052.5, "y": 2704.4, "building": "21", "floor": 6, "room_id": ""}, {"x": 1052.0, "y": 2770.4, "building": "21", "floor": 6, "room_id": ""}, {"x": 1468.0, "y": 3537.3, "building": "21", "floor": 6, "room_id": "21648"}, {"x": 2400.7, "y": 3832.4, "building": "21", "floor": 6, "room_id": "21623"}, {"x": 1608.8, "y": 3489.6, "building": "21", "floor": 6, "room_id": "21649"}, {"x": 2884.0, "y": 2024.4, "building": "21", "floor": 6, "room_id": "21606"}, {"x": 1774.5, "y": 3307.2, "building": "21", "floor": 6, "room_id": "21649"}, {"x": 1773.9, "y": 3397.2, "building": "21", "floor": 6, "room_id": "21649"}, {"x": 1523.4, "y": 2614.6, "building": "21", "floor": 6, "room_id": "21653"}, {"x": 1587.3, "y": 2551.2, "building": "21", "floor": 6, "room_id": "21653"}, {"x": 3244.1, "y": 3893.0, "building": "21", "floor": 6, "room_id": "21616"}, {"x": 1750.1, "y": 3224.8, "building": "21", "floor": 6, "room_id": ""}, {"x": 504.9, "y": 2969.0, "building": "22", "floor": 2, "room_id": ""}, {"x": 609.6, "y": 3073.6, "building": "22", "floor": 2, "room_id": ""}, {"x": 624.4, "y": 3217.3, "building": "22", "floor": 2, "room_id": "22206"}, {"x": 607.2, "y": 3378.3, "building": "22", "floor": 2, "room_id": "22206"}, {"x": -275.6, "y": 2079.9, "building": "22", "floor": 2, "room_id": ""}, {"x": -275.3, "y": 2079.9, "building": "22", "floor": 2, "room_id": ""}, {"x": -1053.1, "y": 2968.6, "building": "22", "floor": 2, "room_id": ""}, {"x": 306.4, "y": 2173.4, "building": "22", "floor": 2, "room_id": ""}, {"x": -854.7, "y": 2169.8, "building": "22", "floor": 2, "room_id": ""}, {"x": -1160.5, "y": 3076.0, "building": "22", "floor": 2, "room_id": "22201"}, {"x": -2326.8, "y": 3422.1, "building": "22", "floor": 2, "room_id": ""}, {"x": -2311.9, "y": 3778.9, "building": "22", "floor": 2, "room_id": ""}, {"x": -1392.2, "y": 3422.9, "building": "22", "floor": 2, "room_id": ""}, {"x": -1479.7, "y": 3721.8, "building": "22", "floor": 2, "room_id": ""}, {"x": -1317.2, "y": 3503.4, "building": "22", "floor": 2, "room_id": "22210"}, {"x": -1215.2, "y": 3503.4, "building": "22", "floor": 2, "room_id": "22210"}, {"x": -2222.7, "y": 3778.9, "building": "22", "floor": 2, "room_id": ""}, {"x": -1274.7, "y": 3802.9, "building": "22", "floor": 2, "room_id": "22210"}, {"x": 826.8, "y": 3501.9, "building": "22", "floor": 2, "room_id": "22206"}, {"x": 553.4, "y": 3498.5, "building": "22", "floor": 2, "room_id": "22206"}, {"x": 482.9, "y": 3435.1, "building": "22", "floor": 2, "room_id": "22206"}, {"x": 338.1, "y": 3761.9, "building": "22", "floor": 2, "room_id": "22207"}, {"x": 355.9, "y": 3763.2, "building": "22", "floor": 2, "room_id": "22207"}, {"x": 423.1, "y": 3761.9, "building": "22", "floor": 2, "room_id": "22207"}, {"x": 518.5, "y": 3753.5, "building": "22", "floor": 2, "room_id": "22207"}, {"x": 508.1, "y": 3761.9, "building": "22", "floor": 2, "room_id": "22207"}, {"x": 584.7, "y": 3687.9, "building": "22", "floor": 2, "room_id": "22207"}, {"x": 846.0, "y": 3776.5, "building": "22", "floor": 2, "room_id": "22208"}, {"x": 773.6, "y": 3757.9, "building": "22", "floor": 2, "room_id": "22208"}, {"x": 731.4, "y": 3687.9, "building": "22", "floor": 2, "room_id": "22208"}, {"x": 925.1, "y": 3673.0, "building": "22", "floor": 2, "room_id": "22208"}, {"x": -380.8, "y": 1973.8, "building": "22", "floor": 3, "room_id": "22312"}, {"x": -167.5, "y": 2053.3, "building": "22", "floor": 3, "room_id": "22315"}, {"x": -373.7, "y": 2053.3, "building": "22", "floor": 3, "room_id": "22311"}, {"x": -233.1, "y": 1901.1, "building": "22", "floor": 3, "room_id": "22313"}, {"x": -922.5, "y": 2514.0, "building": "22", "floor": 3, "room_id": "22310"}, {"x": -1505.3, "y": 3260.2, "building": "22", "floor": 3, "room_id": "22340"}, {"x": -1668.3, "y": 3095.2, "building": "22", "floor": 3, "room_id": "22340"}, {"x": -1550.3, "y": 3159.6, "building": "22", "floor": 3, "room_id": "22340"}, {"x": -1806.3, "y": 3146.5, "building": "22", "floor": 3, "room_id": "22340"}, {"x": -1682.8, "y": 2803.0, "building": "22", "floor": 3, "room_id": "22307"}, {"x": -1682.8, "y": 2803.0, "building": "22", "floor": 3, "room_id": "22307"}, {"x": -1937.8, "y": 2803.0, "building": "22", "floor": 3, "room_id": "22306"}, {"x": -1937.8, "y": 2803.0, "building": "22", "floor": 3, "room_id": "22306"}, {"x": -1606.7, "y": 3602.2, "building": "22", "floor": 3, "room_id": ""}, {"x": -1950.3, "y": 3062.7, "building": "22", "floor": 3, "room_id": "22306"}, {"x": -1736.0, "y": 3056.7, "building": "22", "floor": 3, "room_id": "22340"}, {"x": -1740.0, "y": 3056.7, "building": "22", "floor": 3, "room_id": "22340"}, {"x": -2118.8, "y": 3260.2, "building": "22", "floor": 3, "room_id": "22306"}, {"x": 812.5, "y": 3164.2, "building": "22", "floor": 3, "room_id": "22317"}, {"x": 1395.5, "y": 2713.7, "building": "22", "floor": 3, "room_id": ""}, {"x": 1395.5, "y": 2849.5, "building": "22", "floor": 3, "room_id": ""}, {"x": 1140.5, "y": 2799.2, "building": "22", "floor": 3, "room_id": "22317"}, {"x": 1140.5, "y": 2713.7, "building": "22", "floor": 3, "room_id": ""}, {"x": 1140.5, "y": 2849.5, "building": "22", "floor": 3, "room_id": "22317"}, {"x": 1123.0, "y": 3095.2, "building": "22", "floor": 3, "room_id": "22317"}, {"x": 1342.3, "y": 3056.7, "building": "22", "floor": 3, "room_id": ""}, {"x": 1376.5, "y": 3056.7, "building": "22", "floor": 3, "room_id": ""}, {"x": 1304.0, "y": 3056.7, "building": "22", "floor": 3, "room_id": ""}, {"x": 1214.3, "y": 3056.7, "building": "22", "floor": 3, "room_id": ""}, {"x": 958.0, "y": 3260.2, "building": "22", "floor": 3, "room_id": "22318"}, {"x": -2262.8, "y": 3164.2, "building": "22", "floor": 3, "room_id": "22306"}, {"x": -1939.3, "y": 3056.7, "building": "22", "floor": 3, "room_id": "22306"}, {"x": 1333.5, "y": 3499.9, "building": "22", "floor": 3, "room_id": ""}, {"x": 168.2, "y": 2635.6, "building": "22", "floor": 3, "room_id": "22316"}, {"x": -948.9, "y": 2416.1, "building": "22", "floor": 3, "room_id": "22310"}, {"x": -1091.6, "y": 3106.8, "building": "22", "floor": 3, "room_id": "22308"}, {"x": -1046.7, "y": 3493.1, "building": "22", "floor": 3, "room_id": ""}, {"x": 524.8, "y": 3314.2, "building": "22", "floor": 3, "room_id": "22319"}, {"x": -269.1, "y": 4973.7, "building": "22", "floor": 3, "room_id": "22303"}, {"x": -269.1, "y": 4973.7, "building": "22", "floor": 3, "room_id": "22303"}, {"x": 265.1, "y": 4484.0, "building": "22", "floor": 3, "room_id": "22301"}, {"x": 32.5, "y": 4716.6, "building": "22", "floor": 3, "room_id": "22302"}, {"x": 265.1, "y": 4484.0, "building": "22", "floor": 3, "room_id": "22301"}, {"x": 32.5, "y": 4716.6, "building": "22", "floor": 3, "room_id": "22302"}, {"x": -567.4, "y": 4709.8, "building": "22", "floor": 3, "room_id": "22304"}, {"x": -808.7, "y": 4475.2, "building": "22", "floor": 3, "room_id": "22305"}, {"x": 1052.0, "y": 4732.2, "building": "22", "floor": 3, "room_id": ""}, {"x": 967.0, "y": 4732.2, "building": "22", "floor": 3, "room_id": "22301"}, {"x": -1588.2, "y": 4732.2, "building": "22", "floor": 3, "room_id": ""}, {"x": -1502.9, "y": 4732.2, "building": "22", "floor": 3, "room_id": "22305"}, {"x": -2024.2, "y": 4732.2, "building": "22", "floor": 3, "room_id": ""}, {"x": -2109.2, "y": 4732.2, "building": "22", "floor": 3, "room_id": ""}, {"x": 1333.5, "y": 3499.9, "building": "22", "floor": 3, "room_id": ""}, {"x": 1579.0, "y": 3260.2, "building": "22", "floor": 3, "room_id": ""}, {"x": 1410.0, "y": 3095.2, "building": "22", "floor": 3, "room_id": ""}, {"x": 1528.0, "y": 3159.6, "building": "22", "floor": 3, "room_id": ""}, {"x": 1269.5, "y": 3146.5, "building": "22", "floor": 3, "room_id": ""}, {"x": 1395.5, "y": 2845.7, "building": "22", "floor": 3, "room_id": ""}, {"x": 1140.5, "y": 2849.5, "building": "22", "floor": 3, "room_id": "22317"}, {"x": 1123.0, "y": 3062.7, "building": "22", "floor": 3, "room_id": "22317"}, {"x": 1338.3, "y": 3056.7, "building": "22", "floor": 3, "room_id": ""}, {"x": 1214.3, "y": 3056.7, "building": "22", "floor": 3, "room_id": ""}, {"x": 937.5, "y": 3293.0, "building": "22", "floor": 3, "room_id": "22318"}, {"x": 1471.6, "y": 3608.2, "building": "22", "floor": 3, "room_id": ""}, {"x": 823.0, "y": 3369.2, "building": "22", "floor": 3, "room_id": "22318"}, {"x": 1534.8, "y": 4685.4, "building": "22", "floor": 3, "room_id": ""}, {"x": 1488.0, "y": 4732.2, "building": "22", "floor": 3, "room_id": ""}, {"x": 1572.5, "y": 4732.2, "building": "22", "floor": 3, "room_id": ""}, {"x": -161.1, "y": 1973.2, "building": "22", "floor": 3, "room_id": "22314"}, {"x": -308.1, "y": 4575.3, "building": "22", "floor": 4, "room_id": "22424"}, {"x": -380.8, "y": 4502.6, "building": "22", "floor": 4, "room_id": "22425"}, {"x": -167.5, "y": 4423.1, "building": "22", "floor": 4, "room_id": "22421"}, {"x": -373.7, "y": 4423.1, "building": "22", "floor": 4, "room_id": "22426"}, {"x": -233.1, "y": 4575.3, "building": "22", "floor": 4, "room_id": "22423"}, {"x": -160.4, "y": 4502.6, "building": "22", "floor": 4, "room_id": "22422"}, {"x": -923.5, "y": 3961.4, "building": "22", "floor": 4, "room_id": "22428"}, {"x": -995.6, "y": 3889.2, "building": "22", "floor": 4, "room_id": "22429"}, {"x": -996.0, "y": 3816.8, "building": "22", "floor": 4, "room_id": "22430"}, {"x": -851.0, "y": 3961.7, "building": "22", "floor": 4, "room_id": "22427"}, {"x": 477.8, "y": 3442.3, "building": "22", "floor": 4, "room_id": "22418"}, {"x": 244.8, "y": 3675.3, "building": "22", "floor": 4, "room_id": "22420"}, {"x": -308.1, "y": 1901.1, "building": "22", "floor": 4, "room_id": "22409"}, {"x": -380.8, "y": 1973.8, "building": "22", "floor": 4, "room_id": "22408"}, {"x": -167.5, "y": 2053.3, "building": "22", "floor": 4, "room_id": "22412"}, {"x": -373.7, "y": 2053.3, "building": "22", "floor": 4, "room_id": "22407"}, {"x": -233.1, "y": 1901.1, "building": "22", "floor": 4, "room_id": "22410"}, {"x": -160.4, "y": 1973.8, "building": "22", "floor": 4, "room_id": "22411"}, {"x": 381.9, "y": 2514.7, "building": "22", "floor": 4, "room_id": "22414"}, {"x": 454.1, "y": 2586.9, "building": "22", "floor": 4, "room_id": "22415"}, {"x": 454.1, "y": 2659.0, "building": "22", "floor": 4, "room_id": "22416"}, {"x": 309.8, "y": 2514.7, "building": "22", "floor": 4, "room_id": "22413"}, {"x": -720.2, "y": 2645.5, "building": "22", "floor": 4, "room_id": "22406"}, {"x": -961.0, "y": 2552.6, "building": "22", "floor": 4, "room_id": "22405"}, {"x": -865.2, "y": 2790.5, "building": "22", "floor": 4, "room_id": "22404"}, {"x": -1353.8, "y": 3312.2, "building": "22", "floor": 4, "room_id": "22431"}, {"x": -1353.8, "y": 3164.2, "building": "22", "floor": 4, "room_id": "22403"}, {"x": -1499.3, "y": 3260.2, "building": "22", "floor": 4, "room_id": "22431"}, {"x": -1668.3, "y": 3095.2, "building": "22", "floor": 4, "room_id": "22454"}, {"x": -1550.3, "y": 3159.6, "building": "22", "floor": 4, "room_id": "22454"}, {"x": -1806.3, "y": 3146.5, "building": "22", "floor": 4, "room_id": "22454"}, {"x": -1682.8, "y": 2803.0, "building": "22", "floor": 4, "room_id": "22402"}, {"x": -1682.8, "y": 2803.0, "building": "22", "floor": 4, "room_id": "22402"}, {"x": -1937.8, "y": 2803.0, "building": "22", "floor": 4, "room_id": "22401"}, {"x": -1937.8, "y": 2803.0, "building": "22", "floor": 4, "room_id": "22401"}, {"x": -1606.7, "y": 3602.2, "building": "22", "floor": 4, "room_id": "22431"}, {"x": -1950.3, "y": 3062.7, "building": "22", "floor": 4, "room_id": "22401"}, {"x": -1736.0, "y": 3056.7, "building": "22", "floor": 4, "room_id": "22454"}, {"x": -1740.0, "y": 3056.7, "building": "22", "floor": 4, "room_id": "22454"}, {"x": -2111.3, "y": 3260.2, "building": "22", "floor": 4, "room_id": "22401"}, {"x": 812.5, "y": 3312.2, "building": "22", "floor": 4, "room_id": "22418"}, {"x": 812.5, "y": 3164.2, "building": "22", "floor": 4, "room_id": "22417"}, {"x": 1140.5, "y": 2803.0, "building": "22", "floor": 4, "room_id": "22417"}, {"x": 1140.5, "y": 2803.0, "building": "22", "floor": 4, "room_id": "22417"}, {"x": 1123.0, "y": 3095.2, "building": "22", "floor": 4, "room_id": "22417"}, {"x": 1342.3, "y": 3056.7, "building": "22", "floor": 4, "room_id": ""}, {"x": 1214.3, "y": 3056.7, "building": "22", "floor": 4, "room_id": ""}, {"x": 1272.5, "y": 3056.7, "building": "22", "floor": 4, "room_id": ""}, {"x": 958.0, "y": 3260.2, "building": "22", "floor": 4, "room_id": "22418"}, {"x": -2257.8, "y": 3312.2, "building": "22", "floor": 4, "room_id": ""}, {"x": -2257.8, "y": 3164.2, "building": "22", "floor": 4, "room_id": "22401"}, {"x": -1922.3, "y": 3056.7, "building": "22", "floor": 4, "room_id": "22401"}, {"x": -308.1, "y": 4575.3, "building": "22", "floor": 5, "room_id": "22524"}, {"x": -380.8, "y": 4502.6, "building": "22", "floor": 5, "room_id": "22525"}, {"x": -163.3, "y": 4428.8, "building": "22", "floor": 5, "room_id": "22521"}, {"x": -379.4, "y": 4428.8, "building": "22", "floor": 5, "room_id": "22526"}, {"x": -233.1, "y": 4575.3, "building": "22", "floor": 5, "room_id": "22523"}, {"x": -160.4, "y": 4502.6, "building": "22", "floor": 5, "room_id": "22522"}, {"x": -308.1, "y": 1901.1, "building": "22", "floor": 5, "room_id": "22510"}, {"x": -380.8, "y": 1973.8, "building": "22", "floor": 5, "room_id": "22509"}, {"x": -162.6, "y": 2046.9, "building": "22", "floor": 5, "room_id": "22513"}, {"x": -379.4, "y": 2047.6, "building": "22", "floor": 5, "room_id": "22508"}, {"x": -233.1, "y": 1901.1, "building": "22", "floor": 5, "room_id": "22511"}, {"x": -160.4, "y": 1973.8, "building": "22", "floor": 5, "room_id": "22512"}, {"x": -1353.8, "y": 3313.2, "building": "22", "floor": 5, "room_id": "22528"}, {"x": -1350.8, "y": 3164.2, "building": "22", "floor": 5, "room_id": "22503"}, {"x": -1499.3, "y": 3260.2, "building": "22", "floor": 5, "room_id": "22528"}, {"x": -1668.3, "y": 3095.2, "building": "22", "floor": 5, "room_id": "22502"}, {"x": -1550.3, "y": 3159.6, "building": "22", "floor": 5, "room_id": "22503"}, {"x": -1705.8, "y": 3165.2, "building": "22", "floor": 5, "room_id": "22502"}, {"x": -1810.3, "y": 2794.0, "building": "22", "floor": 5, "room_id": "22501"}, {"x": -1810.3, "y": 2720.0, "building": "22", "floor": 5, "room_id": "22501"}, {"x": -1666.8, "y": 2848.3, "building": "22", "floor": 5, "room_id": "22502"}, {"x": -1953.8, "y": 2848.3, "building": "22", "floor": 5, "room_id": "22501"}, {"x": -1606.7, "y": 3602.2, "building": "22", "floor": 5, "room_id": "22528"}, {"x": -1950.3, "y": 3095.2, "building": "22", "floor": 5, "room_id": "22501"}, {"x": -1736.0, "y": 3056.7, "building": "22", "floor": 5, "room_id": "22502"}, {"x": -1743.5, "y": 3056.7, "building": "22", "floor": 5, "room_id": "22502"}, {"x": -2111.3, "y": 3262.2, "building": "22", "floor": 5, "room_id": "22501"}, {"x": 809.5, "y": 3314.2, "building": "22", "floor": 5, "room_id": "22517"}, {"x": 813.5, "y": 3160.2, "building": "22", "floor": 5, "room_id": "22517"}, {"x": 1140.5, "y": 2803.0, "building": "22", "floor": 5, "room_id": ""}, {"x": 1140.5, "y": 2803.0, "building": "22", "floor": 5, "room_id": ""}, {"x": 1123.0, "y": 3095.2, "building": "22", "floor": 5, "room_id": ""}, {"x": 1342.3, "y": 3056.7, "building": "22", "floor": 5, "room_id": ""}, {"x": 1214.3, "y": 3056.7, "building": "22", "floor": 5, "room_id": ""}, {"x": 1272.5, "y": 3056.7, "building": "22", "floor": 5, "room_id": ""}, {"x": 958.0, "y": 3260.2, "building": "22", "floor": 5, "room_id": "22517"}, {"x": -2263.8, "y": 3314.2, "building": "22", "floor": 5, "room_id": ""}, {"x": -2261.8, "y": 3162.2, "building": "22", "floor": 5, "room_id": "22501"}, {"x": -1929.3, "y": 3056.7, "building": "22", "floor": 5, "room_id": "22501"}, {"x": 441.5, "y": 2780.8, "building": "22", "floor": 5, "room_id": "22516"}, {"x": 503.3, "y": 2646.8, "building": "22", "floor": 5, "room_id": "22516"}, {"x": 179.8, "y": 2519.1, "building": "22", "floor": 5, "room_id": "22514"}, {"x": 107.5, "y": 2519.3, "building": "22", "floor": 5, "room_id": "22514"}, {"x": -992.7, "y": 2661.7, "building": "22", "floor": 5, "room_id": "22504"}, {"x": -920.0, "y": 2518.6, "building": "22", "floor": 5, "room_id": "22506"}, {"x": -992.1, "y": 2590.7, "building": "22", "floor": 5, "room_id": "22505"}, {"x": -846.3, "y": 2515.3, "building": "22", "floor": 5, "room_id": "22507"}, {"x": 449.2, "y": 3815.9, "building": "22", "floor": 5, "room_id": "22518"}, {"x": 449.1, "y": 3889.6, "building": "22", "floor": 5, "room_id": "22519"}, {"x": 377.0, "y": 3961.7, "building": "22", "floor": 5, "room_id": "22519"}, {"x": 303.5, "y": 3961.7, "building": "22", "floor": 5, "room_id": "22520"}, {"x": -734.3, "y": 3811.4, "building": "22", "floor": 5, "room_id": "22527"}, {"x": 1276.5, "y": 3165.2, "building": "22", "floor": 5, "room_id": ""}, {"x": -1844.3, "y": 3165.2, "building": "22", "floor": 5, "room_id": "22501"}, {"x": 137.3, "y": 2747.0, "building": "22", "floor": 6, "room_id": "22603"}, {"x": 85.1, "y": 2700.2, "building": "22", "floor": 6, "room_id": "22603"}, {"x": -307.4, "y": 1846.5, "building": "22", "floor": 6, "room_id": ""}, {"x": -1324.0, "y": 3227.8, "building": "22", "floor": 6, "room_id": "22601"}, {"x": -1231.4, "y": 3232.5, "building": "22", "floor": 6, "room_id": "22601"}, {"x": -2071.6, "y": 3107.2, "building": "22", "floor": 6, "room_id": "22652"}, {"x": -1596.5, "y": 3109.2, "building": "22", "floor": 6, "room_id": "22653"}, {"x": -1802.0, "y": 3097.7, "building": "22", "floor": 6, "room_id": "22652"}, {"x": -1651.1, "y": 2776.0, "building": "22", "floor": 6, "room_id": "22653"}, {"x": -1650.8, "y": 2710.1, "building": "22", "floor": 6, "room_id": "22653"}, {"x": -1651.5, "y": 2868.0, "building": "22", "floor": 6, "room_id": "22653"}, {"x": -1651.2, "y": 2802.1, "building": "22", "floor": 6, "room_id": "22653"}, {"x": -1651.9, "y": 2960.0, "building": "22", "floor": 6, "room_id": "22653"}, {"x": -1651.6, "y": 2894.1, "building": "22", "floor": 6, "room_id": "22653"}, {"x": -2024.1, "y": 2774.4, "building": "22", "floor": 6, "room_id": "22651"}, {"x": -2023.8, "y": 2708.4, "building": "22", "floor": 6, "room_id": "22651"}, {"x": -2024.5, "y": 2866.4, "building": "22", "floor": 6, "room_id": "22651"}, {"x": -2024.2, "y": 2800.4, "building": "22", "floor": 6, "room_id": "22651"}, {"x": -2025.0, "y": 2958.4, "building": "22", "floor": 6, "room_id": "22651"}, {"x": -2024.7, "y": 2892.4, "building": "22", "floor": 6, "room_id": "22651"}, {"x": -1464.3, "y": 3511.9, "building": "22", "floor": 6, "room_id": "22607"}, {"x": 1036.0, "y": 3094.0, "building": "22", "floor": 6, "room_id": ""}, {"x": 1429.0, "y": 2871.1, "building": "22", "floor": 6, "room_id": ""}, {"x": 1428.2, "y": 2963.1, "building": "22", "floor": 6, "room_id": ""}, {"x": 1428.8, "y": 2897.2, "building": "22", "floor": 6, "room_id": ""}, {"x": 1059.7, "y": 3010.0, "building": "22", "floor": 6, "room_id": ""}, {"x": 1060.5, "y": 2910.0, "building": "22", "floor": 6, "room_id": ""}, {"x": 1060.0, "y": 2976.0, "building": "22", "floor": 6, "room_id": ""}, {"x": 1061.4, "y": 2810.0, "building": "22", "floor": 6, "room_id": ""}, {"x": 1060.9, "y": 2876.0, "building": "22", "floor": 6, "room_id": ""}, {"x": 1062.3, "y": 2710.1, "building": "22", "floor": 6, "room_id": ""}, {"x": 1061.7, "y": 2776.0, "building": "22", "floor": 6, "room_id": ""}, {"x": -650.2, "y": 3868.9, "building": "22", "floor": 6, "room_id": "22606"}, {"x": -567.9, "y": 3871.6, "building": "22", "floor": 6, "room_id": ""}, {"x": -683.5, "y": 3835.3, "building": "22", "floor": 6, "room_id": "22606"}]